rasa_nlu_gao/__init__.py
rasa_nlu_gao/components.py
rasa_nlu_gao/config.py
rasa_nlu_gao/convert.py
rasa_nlu_gao/data_router.py
rasa_nlu_gao/evaluate.py
rasa_nlu_gao/model.py
rasa_nlu_gao/persistor.py
rasa_nlu_gao/project.py
rasa_nlu_gao/registry.py
rasa_nlu_gao/run.py
rasa_nlu_gao/server.py
rasa_nlu_gao/train.py
rasa_nlu_gao/version.py
rasa_nlu_gao/classifiers/__init__.py
rasa_nlu_gao/classifiers/embedding_bert_intent_classifier.py
rasa_nlu_gao/classifiers/embedding_bert_intent_estimator_classifier.py
rasa_nlu_gao/classifiers/embedding_intent_classifier.py
rasa_nlu_gao/classifiers/entity_edit_intent.py
rasa_nlu_gao/classifiers/kashgari_intent_classifier.py
rasa_nlu_gao/classifiers/keyword_intent_classifier.py
rasa_nlu_gao/classifiers/mitie_intent_classifier.py
rasa_nlu_gao/classifiers/sklearn_intent_classifier.py
rasa_nlu_gao/emulators/__init__.py
rasa_nlu_gao/emulators/dialogflow.py
rasa_nlu_gao/emulators/luis.py
rasa_nlu_gao/emulators/wit.py
rasa_nlu_gao/extractors/__init__.py
rasa_nlu_gao/extractors/bilstm_crf_entity_extractor.py
rasa_nlu_gao/extractors/crf_entity_extractor.py
rasa_nlu_gao/extractors/duckling_extractor.py
rasa_nlu_gao/extractors/duckling_http_extractor.py
rasa_nlu_gao/extractors/entity_synonyms.py
rasa_nlu_gao/extractors/jieba_pseg_extractor.py
rasa_nlu_gao/extractors/kashgari_entity_extractor.py
rasa_nlu_gao/extractors/mitie_entity_extractor.py
rasa_nlu_gao/extractors/pyltp_extractor.py
rasa_nlu_gao/extractors/spacy_entity_extractor.py
rasa_nlu_gao/featurizers/__init__.py
rasa_nlu_gao/featurizers/bert_vectors_featurizer.py
rasa_nlu_gao/featurizers/count_vectors_featurizer.py
rasa_nlu_gao/featurizers/intent_featurizer_wordvector.py
rasa_nlu_gao/featurizers/mitie_featurizer.py
rasa_nlu_gao/featurizers/ngram_featurizer.py
rasa_nlu_gao/featurizers/regex_featurizer.py
rasa_nlu_gao/featurizers/spacy_featurizer.py
rasa_nlu_gao/models/__init__.py
rasa_nlu_gao/models/bert_client.py
rasa_nlu_gao/models/lenet.py
rasa_nlu_gao/models/model.py
rasa_nlu_gao-1.0.3.dist-info/LICENSE.txt
rasa_nlu_gao-1.0.3.dist-info/METADATA
rasa_nlu_gao-1.0.3.dist-info/WHEEL
rasa_nlu_gao-1.0.3.dist-info/top_level.txt
rasa_nlu_gao-1.0.3.dist-info/RECORD
