Metadata-Version: 2.1
Name: rasa-nlu-gao
Version: 1.0.3
Summary: Rasa NLU addons a natural language parser for bots
Home-page: https://rasa.com
Author: Gao Quan
Author-email: gaoquan199035@gmail.com
Maintainer: Gao Quan
Maintainer-email: gaoquan199035@gmail.com
License: Apache 2.0
Download-URL: https://github.com/GaoQ1/rasa_nlu_gq/archive/v1.0.3.tar.gz
Project-URL: Bug Reports, https://github.com/GaoQ1/rasa_nlu_gq/issues
Project-URL: Source, https://github.com/GaoQ1/rasa_nlu_gq
Keywords: nlp machine-learning machine-learning-library bot bots botkit rasa conversational-agents conversational-ai chatbotchatbot-framework bot-framework
Platform: UNKNOWN
Requires-Dist: rasa (~=1.1.3)
Requires-Dist: jieba (~=0.39)
Requires-Dist: bert-serving-client (==1.8.9)
Requires-Dist: tensorflow (==1.14.0)
Requires-Dist: kashgari-tf (~=0.5.3)
